conftier/__init__.py
conftier/cli.py
conftier/core.py
conftier/utils/__init__.py
conftier/utils/logger.py
conftier-0.2.1.dist-info/METADATA
conftier-0.2.1.dist-info/WHEEL
conftier-0.2.1.dist-info/entry_points.txt
conftier-0.2.1.dist-info/RECORD
