Metadata-Version: 2.1
Name: conftier
Version: 0.2.1
Summary: Multi-level configuration framework
Home-page: https://github.com/Undertone0809/conftier
License: MIT
Author: conftier
Author-email: zeeland4work@gmail.com
Requires-Python: >=3.9,<4.0
Classifier: Development Status :: 3 - Alpha
Classifier: Intended Audience :: Developers
Classifier: License :: OSI Approved :: MIT License
Classifier: Operating System :: OS Independent
Classifier: Programming Language :: Python :: 3
Classifier: Programming Language :: Python :: 3.9
Classifier: Programming Language :: Python :: 3.10
Classifier: Programming Language :: Python :: 3.11
Classifier: Programming Language :: Python :: 3.12
Classifier: Programming Language :: Python :: 3.8
Classifier: Topic :: Software Development :: Libraries :: Python Modules
Provides-Extra: pydantic
Requires-Dist: pydantic (>=2.0.0,<3.0.0) ; extra == "pydantic"
Requires-Dist: rich (>=10.14.0,<11.0.0)
Requires-Dist: typer[all] (>=0.4.0,<0.5.0)
Requires-Dist: zeeland (>=0.3.0,<0.4.0)
Project-URL: Repository, https://github.com/Undertone0809/conftier
